<citas>
    <cita>
        <fecha>29/12/2020</fecha>
        <titulo>Reunión General</titulo>
        <descrip>Reunión en la sede donostiarra con lo socios de Hernani</descrip>
    </cita>
    <cita>
        <fecha>31/12/2020</fecha>
        <titulo>Dia Libre</titulo>
        <descrip>Dia libre para todos los empleados por fin de año</descrip>
    </cita>
    <cita>
        <fecha>1/1/2021</fecha>
        <titulo>Año nuevo</titulo>
        <descrip>Festivo, dia libre por celebración año nuevo</descrip>
    </cita>
    <cita>
        <fecha>10/1/2020</fecha>
        <titulo>Barcelona</titulo>
        <descrip>Videollamada con la sede de Barcelona</descrip>
    </cita>
    <cita>
        <fecha>2/12/2020</fecha>
        <titulo>Vuelta</titulo>
        <descrip>Vuelta al trabajo tras año nuevo</descrip>
    </cita>
</citas>